{"type": "FeatureCollection", "name": "osm_gis_osm_natural_free_1_preview", "crs": {"type": "name", "properties": {"name": "urn:ogc:def:crs:OGC:1.3:CRS84"}}, "features": [{"type": "Feature", "properties": {"fclass": "peak", "name": "Cabeça Alta"}, "geometry": {"type": "Point", "coordinates": [-7.49386, 39.18646]}}, {"type": "Feature", "properties": {"fclass": "peak", "name": "São Martinho"}, "geometry": {"type": "Point", "coordinates": [-7.58748, 39.20958]}}, {"type": "Feature", "properties": {"fclass": "tree", "name": null}, "geometry": {"type": "Point", "coordinates": [-7.64863, 39.30659]}}, {"type": "Feature", "properties": {"fclass": "tree", "name": null}, "geometry": {"type": "Point", "coordinates": [-7.64854, 39.30669]}}, {"type": "Feature", "properties": {"fclass": "tree", "name": null}, "geometry": {"type": "Point", "coordinates": [-7.64882, 39.30669]}}, {"type": "Feature", "properties": {"fclass": "tree", "name": null}, "geometry": {"type": "Point", "coordinates": [-7.64872, 39.30671]}}, {"type": "Feature", "properties": {"fclass": "tree", "name": null}, "geometry": {"type": "Point", "coordinates": [-7.64866, 39.30671]}}, {"type": "Feature", "properties": {"fclass": "tree", "name": null}, "geometry": {"type": "Point", "coordinates": [-7.64892, 39.30675]}}, {"type": "Feature", "properties": {"fclass": "tree", "name": null}, "geometry": {"type": "Point", "coordinates": [-7.64885, 39.30677]}}, {"type": "Feature", "properties": {"fclass": "tree", "name": null}, "geometry": {"type": "Point", "coordinates": [-7.69478, 39.32594]}}, {"type": "Feature", "properties": {"fclass": "tree", "name": null}, "geometry": {"type": "Point", "coordinates": [-7.69485, 39.32596]}}, {"type": "Feature", "properties": {"fclass": "tree", "name": null}, "geometry": {"type": "Point", "coordinates": [-7.69487, 39.326]}}, {"type": "Feature", "properties": {"fclass": "tree", "name": null}, "geometry": {"type": "Point", "coordinates": [-7.69494, 39.32601]}}, {"type": "Feature", "properties": {"fclass": "tree", "name": null}, "geometry": {"type": "Point", "coordinates": [-7.69503, 39.32607]}}, {"type": "Feature", "properties": {"fclass": "tree", "name": null}, "geometry": {"type": "Point", "coordinates": [-7.69425, 39.32607]}}, {"type": "Feature", "properties": {"fclass": "tree", "name": null}, "geometry": {"type": "Point", "coordinates": [-7.69503, 39.32617]}}, {"type": "Feature", "properties": {"fclass": "tree", "name": null}, "geometry": {"type": "Point", "coordinates": [-7.69491, 39.32619]}}, {"type": "Feature", "properties": {"fclass": "tree", "name": null}, "geometry": {"type": "Point", "coordinates": [-7.69453, 39.32623]}}, {"type": "Feature", "properties": {"fclass": "tree", "name": null}, "geometry": {"type": "Point", "coordinates": [-7.6966, 39.32633]}}]}