{"type": "FeatureCollection", "name": "osm_gis_osm_natural_free_1_preview", "crs": {"type": "name", "properties": {"name": "urn:ogc:def:crs:OGC:1.3:CRS84"}}, "features": [{"type": "Feature", "properties": {"fclass": "tree", "name": null}, "geometry": {"type": "Point", "coordinates": [-8.57731, 39.24865]}}, {"type": "Feature", "properties": {"fclass": "tree", "name": null}, "geometry": {"type": "Point", "coordinates": [-8.57743, 39.24865]}}, {"type": "Feature", "properties": {"fclass": "tree", "name": null}, "geometry": {"type": "Point", "coordinates": [-8.5773, 39.24872]}}, {"type": "Feature", "properties": {"fclass": "tree", "name": null}, "geometry": {"type": "Point", "coordinates": [-8.57743, 39.24873]}}, {"type": "Feature", "properties": {"fclass": "tree", "name": null}, "geometry": {"type": "Point", "coordinates": [-8.5774, 39.2488]}}, {"type": "Feature", "properties": {"fclass": "tree", "name": null}, "geometry": {"type": "Point", "coordinates": [-8.57757, 39.24919]}}, {"type": "Feature", "properties": {"fclass": "tree", "name": null}, "geometry": {"type": "Point", "coordinates": [-8.57773, 39.2492]}}, {"type": "Feature", "properties": {"fclass": "tree", "name": null}, "geometry": {"type": "Point", "coordinates": [-8.57798, 39.24921]}}, {"type": "Feature", "properties": {"fclass": "tree", "name": null}, "geometry": {"type": "Point", "coordinates": [-8.57821, 39.24924]}}, {"type": "Feature", "properties": {"fclass": "tree", "name": null}, "geometry": {"type": "Point", "coordinates": [-8.57837, 39.24925]}}, {"type": "Feature", "properties": {"fclass": "tree", "name": null}, "geometry": {"type": "Point", "coordinates": [-8.57256, 39.25326]}}, {"type": "Feature", "properties": {"fclass": "tree", "name": null}, "geometry": {"type": "Point", "coordinates": [-8.57265, 39.25332]}}, {"type": "Feature", "properties": {"fclass": "tree", "name": null}, "geometry": {"type": "Point", "coordinates": [-8.57273, 39.25338]}}, {"type": "Feature", "properties": {"fclass": "tree", "name": null}, "geometry": {"type": "Point", "coordinates": [-8.57236, 39.25341]}}, {"type": "Feature", "properties": {"fclass": "tree", "name": null}, "geometry": {"type": "Point", "coordinates": [-8.57264, 39.25347]}}, {"type": "Feature", "properties": {"fclass": "tree", "name": null}, "geometry": {"type": "Point", "coordinates": [-8.57245, 39.25348]}}, {"type": "Feature", "properties": {"fclass": "tree", "name": null}, "geometry": {"type": "Point", "coordinates": [-8.57256, 39.25355]}}, {"type": "Feature", "properties": {"fclass": "tree", "name": null}, "geometry": {"type": "Point", "coordinates": [-8.57195, 39.25369]}}, {"type": "Feature", "properties": {"fclass": "tree", "name": null}, "geometry": {"type": "Point", "coordinates": [-8.57203, 39.25377]}}, {"type": "Feature", "properties": {"fclass": "tree", "name": null}, "geometry": {"type": "Point", "coordinates": [-8.5721, 39.25383]}}, {"type": "Feature", "properties": {"fclass": "tree", "name": null}, "geometry": {"type": "Point", "coordinates": [-8.57835, 39.24931]}}, {"type": "Feature", "properties": {"fclass": "tree", "name": null}, "geometry": {"type": "Point", "coordinates": [-8.5772, 39.24935]}}, {"type": "Feature", "properties": {"fclass": "tree", "name": null}, "geometry": {"type": "Point", "coordinates": [-8.57798, 39.24973]}}, {"type": "Feature", "properties": {"fclass": "tree", "name": null}, "geometry": {"type": "Point", "coordinates": [-8.58006, 39.24982]}}, {"type": "Feature", "properties": {"fclass": "tree", "name": null}, "geometry": {"type": "Point", "coordinates": [-8.57708, 39.26672]}}, {"type": "Feature", "properties": {"fclass": "tree", "name": null}, "geometry": {"type": "Point", "coordinates": [-8.577, 39.26692]}}, {"type": "Feature", "properties": {"fclass": "tree", "name": null}, "geometry": {"type": "Point", "coordinates": [-8.57664, 39.2671]}}, {"type": "Feature", "properties": {"fclass": "tree", "name": null}, "geometry": {"type": "Point", "coordinates": [-8.57652, 39.26719]}}, {"type": "Feature", "properties": {"fclass": "tree", "name": null}, "geometry": {"type": "Point", "coordinates": [-8.57687, 39.2673]}}]}